algorun/__init__.py
algorun/__main__.py
algorun/cli/__init__.py
algorun/cli/config.py
algorun/cli/goal.py
algorun/cli/reset.py
algorun/cli/start.py
algorun/cli/stop.py
algorun/core/__init__.py
algorun/core/atomic_write.py
algorun/core/conf.py
algorun/core/doctor.py
algorun/core/init.py
algorun/core/log_handlers.py
algorun/core/proc.py
algorun/core/questionary_extensions.py
algorun/core/sandbox.py
algorun/core/utils.py
algorun/core/version_prompt.py
algorun/py.typed
algorun-0.0.1b4.dist-info/LICENSE
algorun-0.0.1b4.dist-info/METADATA
algorun-0.0.1b4.dist-info/WHEEL
algorun-0.0.1b4.dist-info/entry_points.txt
algorun-0.0.1b4.dist-info/RECORD
