Metadata-Version: 2.1
Name: algorun
Version: 0.0.1b4
Summary: Algorand development kit command-line interface
License: MIT
Author: Algorand Foundation
Author-email: contact@algorand.foundation
Requires-Python: >=3.10,<4.0
Classifier: License :: OSI Approved :: MIT License
Classifier: Programming Language :: Python :: 3
Classifier: Programming Language :: Python :: 3.10
Classifier: Programming Language :: Python :: 3.11
Requires-Dist: algokit-client-generator (>=1.0.1,<2.0.0)
Requires-Dist: click (>=8.1.3,<9.0.0)
Requires-Dist: copier (>=7.1.0,<8.0.0)
Requires-Dist: httpx (>=0.23.1,<0.24.0)
Requires-Dist: pyclip (>=0.7.0,<0.8.0)
Requires-Dist: questionary (>=1.10.0,<2.0.0)
Requires-Dist: shellingham (>=1.5.0.post1,<2.0.0)
Requires-Dist: tomli (>=2.0.1,<3.0.0) ; python_version < "3.11"
